{
  "firstLayout": "",
  "gdVersion": {
    "build": 99,
    "major": 4,
    "minor": 0,
    "revision": 0
  },
  "properties": {
    "adaptGameResolutionAtRuntime": true,
    "folderProject": false,
    "orientation": "landscape",
    "packageName": "com.Gdevelop",
    "pixelsRounding": false,
    "projectUuid": "79042898-0a4f-4b0d-ae3b-615548c3d4bb",
    "scaleMode": "linear",
    "sizeOnStartupMode": "adaptWidth",
    "templateSlug": "",
    "useExternalSourceFiles": false,
    "version": "1.2.0",
    "name": "Jumping Stickman",
    "description": "Jump to the top platform",
    "author": "Daniel Yorke",
    "windowWidth": 800,
    "windowHeight": 600,
    "latestCompilationDirectory": "C:\\Users\\danie\\Documents\\GDevelop projects\\Jump_Up",
    "maxFPS": 60,
    "minFPS": 20,
    "verticalSync": false,
    "platformSpecificAssets": {},
    "loadingScreen": {
      "backgroundColor": 0,
      "backgroundFadeInDuration": 0.2,
      "backgroundImageResourceName": "",
      "gdevelopLogoStyle": "light",
      "logoAndProgressFadeInDuration": 0.2,
      "logoAndProgressLogoFadeInDelay": 0.2,
      "minDuration": 1.5,
      "progressBarColor": 16777215,
      "progressBarHeight": 20,
      "progressBarMaxWidth": 200,
      "progressBarMinWidth": 40,
      "progressBarWidthPercent": 30,
      "showGDevelopSplash": true,
      "showProgressBar": true
    },
    "authorIds": [],
    "categories": [],
    "playableDevices": [],
    "extensionProperties": [],
    "platforms": [
      {
        "name": "GDevelop JS platform"
      }
    ],
    "currentPlatform": "GDevelop JS platform"
  },
  "resources": {
    "resources": [
      {
        "alwaysLoaded": false,
        "file": "Ground-1.png",
        "kind": "image",
        "metadata": "",
        "name": "Ground-1.png",
        "smoothed": true,
        "userAdded": false
      },
      {
        "alwaysLoaded": false,
        "file": "Ground-1-1.png",
        "kind": "image",
        "metadata": "",
        "name": "Ground-1-1.png",
        "smoothed": true,
        "userAdded": false
      },
      {
        "alwaysLoaded": false,
        "file": "Player_Sprite-1.png",
        "kind": "image",
        "metadata": "",
        "name": "Player_Sprite-1.png",
        "smoothed": true,
        "userAdded": false
      },
      {
        "alwaysLoaded": false,
        "file": "Player_Sprite-1-0.png",
        "kind": "image",
        "metadata": "",
        "name": "Player_Sprite-1-0.png",
        "smoothed": true,
        "userAdded": true
      },
      {
        "alwaysLoaded": false,
        "file": "Player_Sprite-1-1.png",
        "kind": "image",
        "metadata": "",
        "name": "Player_Sprite-1-1.png",
        "smoothed": true,
        "userAdded": true
      },
      {
        "alwaysLoaded": false,
        "file": "Crown-1.png",
        "kind": "image",
        "metadata": "",
        "name": "Crown-1.png",
        "smoothed": true,
        "userAdded": true
      },
      {
        "alwaysLoaded": false,
        "file": "Ladder_Sprite-1.png",
        "kind": "image",
        "metadata": "",
        "name": "Ladder_Sprite-1.png",
        "smoothed": true,
        "userAdded": true
      },
      {
        "alwaysLoaded": false,
        "file": "Ladder_Sprite-1-1.png",
        "kind": "image",
        "metadata": "",
        "name": "Ladder_Sprite-1-1.png",
        "smoothed": true,
        "userAdded": true
      },
      {
        "alwaysLoaded": false,
        "file": "hidden_Platform-1.png",
        "kind": "image",
        "metadata": "",
        "name": "hidden_Platform-1.png",
        "smoothed": true,
        "userAdded": false
      },
      {
        "alwaysLoaded": false,
        "file": "tile_0111.png",
        "kind": "image",
        "metadata": "",
        "name": "tile_0111.png",
        "smoothed": true,
        "userAdded": false
      },
      {
        "alwaysLoaded": false,
        "file": "tile_0113.png",
        "kind": "image",
        "metadata": "",
        "name": "tile_0113.png",
        "smoothed": true,
        "userAdded": false
      },
      {
        "alwaysLoaded": false,
        "file": "tile_01112.png",
        "kind": "image",
        "metadata": "",
        "name": "tile_01112.png",
        "smoothed": true,
        "userAdded": true
      },
      {
        "alwaysLoaded": false,
        "file": "tile_0009.png",
        "kind": "image",
        "metadata": "",
        "name": "tile_0009.png",
        "smoothed": true,
        "userAdded": false
      },
      {
        "alwaysLoaded": false,
        "file": "tile_0065.png",
        "kind": "image",
        "metadata": "",
        "name": "tile_0065.png",
        "smoothed": true,
        "userAdded": false
      },
      {
        "alwaysLoaded": false,
        "file": "tile_0258.png",
        "kind": "image",
        "metadata": "",
        "name": "tile_0258.png",
        "smoothed": true,
        "userAdded": true
      },
      {
        "alwaysLoaded": false,
        "file": "tile_0040.png",
        "kind": "image",
        "metadata": "",
        "name": "tile_0040.png",
        "smoothed": true,
        "userAdded": true
      },
      {
        "alwaysLoaded": false,
        "file": "tile_0041.png",
        "kind": "image",
        "metadata": "",
        "name": "tile_0041.png",
        "smoothed": true,
        "userAdded": false
      },
      {
        "alwaysLoaded": false,
        "file": "tile_0042.png",
        "kind": "image",
        "metadata": "",
        "name": "tile_0042.png",
        "smoothed": true,
        "userAdded": true
      },
      {
        "alwaysLoaded": false,
        "file": "Jumping-1.png",
        "kind": "image",
        "metadata": "",
        "name": "Jumping-1.png",
        "smoothed": true,
        "userAdded": false
      },
      {
        "alwaysLoaded": false,
        "file": "Ground-1-1-1.png",
        "kind": "image",
        "metadata": "",
        "name": "Ground-1-1-1.png",
        "smoothed": true,
        "userAdded": false
      },
      {
        "alwaysLoaded": false,
        "file": "Player_Sprite-1-2.png",
        "kind": "image",
        "metadata": "",
        "name": "Player_Sprite-1-2.png",
        "smoothed": true,
        "userAdded": false
      },
      {
        "alwaysLoaded": false,
        "file": "Player_Sprite-running.1.png",
        "kind": "image",
        "metadata": "",
        "name": "Player_Sprite-running.1.png",
        "smoothed": true,
        "userAdded": false
      },
      {
        "alwaysLoaded": false,
        "file": "Idle-1.png",
        "kind": "image",
        "metadata": "",
        "name": "Idle-1.png",
        "smoothed": true,
        "userAdded": true
      },
      {
        "alwaysLoaded": false,
        "file": "Jumping-1-0.png",
        "kind": "image",
        "metadata": "",
        "name": "Jumping-1-0.png",
        "smoothed": true,
        "userAdded": true
      },
      {
        "alwaysLoaded": false,
        "file": "Player_Sprite-running.2.png",
        "kind": "image",
        "metadata": "",
        "name": "Player_Sprite-running.2.png",
        "smoothed": true,
        "userAdded": true
      },
      {
        "alwaysLoaded": false,
        "file": "Running-1.png",
        "kind": "image",
        "metadata": "",
        "name": "Running-1.png",
        "smoothed": true,
        "userAdded": true
      },
      {
        "alwaysLoaded": false,
        "file": "Running-2.png",
        "kind": "image",
        "metadata": "",
        "name": "Running-2.png",
        "smoothed": true,
        "userAdded": true
      },
      {
        "alwaysLoaded": false,
        "file": "ladder climb.png",
        "kind": "image",
        "metadata": "",
        "name": "ladder climb.png",
        "smoothed": true,
        "userAdded": true
      },
      {
        "alwaysLoaded": false,
        "file": "Ladder-1.png",
        "kind": "image",
        "metadata": "",
        "name": "Ladder-1.png",
        "smoothed": true,
        "userAdded": true
      },
      {
        "alwaysLoaded": false,
        "file": "movementArrow-1.png",
        "kind": "image",
        "metadata": "",
        "name": "movementArrow-1.png",
        "smoothed": true,
        "userAdded": false
      },
      {
        "alwaysLoaded": false,
        "file": "tile_0011.png",
        "kind": "image",
        "metadata": "",
        "name": "tile_0011.png",
        "smoothed": true,
        "userAdded": true
      },
      {
        "alwaysLoaded": false,
        "file": "tile_0120.png",
        "kind": "image",
        "metadata": "",
        "name": "tile_0120.png",
        "smoothed": true,
        "userAdded": true
      },
      {
        "file": "mixkit-player-jumping-in-a-video-game-2043.wav",
        "kind": "audio",
        "metadata": "",
        "name": "mixkit-player-jumping-in-a-video-game-2043.wav",
        "preloadAsMusic": false,
        "preloadAsSound": false,
        "userAdded": true
      },
      {
        "file": "mixkit-arcade-retro-changing-tab-206.wav",
        "kind": "audio",
        "metadata": "",
        "name": "mixkit-arcade-retro-changing-tab-206.wav",
        "preloadAsMusic": false,
        "preloadAsSound": false,
        "userAdded": true
      },
      {
        "alwaysLoaded": false,
        "file": "tile_0253.png",
        "kind": "image",
        "metadata": "",
        "name": "tile_0253.png",
        "smoothed": true,
        "userAdded": true
      },
      {
        "alwaysLoaded": false,
        "file": "tile_0000.png",
        "kind": "image",
        "metadata": "",
        "name": "tile_0000.png",
        "smoothed": true,
        "userAdded": true
      },
      {
        "alwaysLoaded": false,
        "file": "tile_0209.png",
        "kind": "image",
        "metadata": "",
        "name": "tile_0209.png",
        "smoothed": true,
        "userAdded": true
      }
    ],
    "resourceFolders": []
  },
  "objects": [
    {
      "assetStoreId": "",
      "name": "Player",
      "tags": "",
      "type": "Sprite",
      "updateIfNotVisible": false,
      "variables": [],
      "effects": [],
      "behaviors": [
        {
          "name": "PlatformerObject",
          "type": "PlatformBehavior::PlatformerObjectBehavior",
          "acceleration": 1500,
          "canGoDownFromJumpthru": true,
          "canGrabPlatforms": false,
          "canGrabWithoutMoving": true,
          "deceleration": 1500,
          "gravity": 1000,
          "ignoreDefaultControls": false,
          "jumpSpeed": 600,
          "jumpSustainTime": 0.2,
          "ladderClimbingSpeed": 150,
          "maxFallingSpeed": 700,
          "maxSpeed": 250,
          "slopeMaxAngle": 60,
          "useLegacyTrajectory": false,
          "xGrabTolerance": 10,
          "yGrabOffset": 0
        }
      ],
      "animations": [
        {
          "name": "Idle",
          "useMultipleDirections": false,
          "directions": [
            {
              "looping": false,
              "timeBetweenFrames": 0.07999999821186066,
              "sprites": [
                {
                  "hasCustomCollisionMask": false,
                  "image": "Idle-1.png",
                  "points": [],
                  "originPoint": {
                    "name": "origine",
                    "x": 0,
                    "y": 0
                  },
                  "centerPoint": {
                    "automatic": true,
                    "name": "centre",
                    "x": 0,
                    "y": 0
                  },
                  "customCollisionMask": []
                }
              ]
            }
          ]
        },
        {
          "name": "Jumping",
          "useMultipleDirections": false,
          "directions": [
            {
              "looping": false,
              "timeBetweenFrames": 0.07999999821186066,
              "sprites": [
                {
                  "hasCustomCollisionMask": false,
                  "image": "Jumping-1-0.png",
                  "points": [],
                  "originPoint": {
                    "name": "origine",
                    "x": 0,
                    "y": 0
                  },
                  "centerPoint": {
                    "automatic": true,
                    "name": "centre",
                    "x": 0,
                    "y": 0
                  },
                  "customCollisionMask": []
                }
              ]
            }
          ]
        },
        {
          "name": "Running",
          "useMultipleDirections": false,
          "directions": [
            {
              "looping": true,
              "timeBetweenFrames": 0.5,
              "sprites": [
                {
                  "hasCustomCollisionMask": false,
                  "image": "Running-1.png",
                  "points": [],
                  "originPoint": {
                    "name": "origine",
                    "x": 0,
                    "y": 0
                  },
                  "centerPoint": {
                    "automatic": true,
                    "name": "centre",
                    "x": 0,
                    "y": 0
                  },
                  "customCollisionMask": []
                },
                {
                  "hasCustomCollisionMask": false,
                  "image": "Running-2.png",
                  "points": [],
                  "originPoint": {
                    "name": "origine",
                    "x": 0,
                    "y": 0
                  },
                  "centerPoint": {
                    "automatic": true,
                    "name": "centre",
                    "x": 0,
                    "y": 0
                  },
                  "customCollisionMask": []
                },
                {
                  "hasCustomCollisionMask": false,
                  "image": "Player_Sprite-running.1.png",
                  "points": [],
                  "originPoint": {
                    "name": "origine",
                    "x": 0,
                    "y": 0
                  },
                  "centerPoint": {
                    "automatic": true,
                    "name": "centre",
                    "x": 0,
                    "y": 0
                  },
                  "customCollisionMask": []
                },
                {
                  "hasCustomCollisionMask": false,
                  "image": "Running-1.png",
                  "points": [],
                  "originPoint": {
                    "name": "origine",
                    "x": 0,
                    "y": 0
                  },
                  "centerPoint": {
                    "automatic": true,
                    "name": "centre",
                    "x": 0,
                    "y": 0
                  },
                  "customCollisionMask": []
                }
              ]
            }
          ]
        },
        {
          "name": "Ladder",
          "useMultipleDirections": false,
          "directions": [
            {
              "looping": false,
              "timeBetweenFrames": 0.07999999821186066,
              "sprites": [
                {
                  "hasCustomCollisionMask": false,
                  "image": "Ladder-1.png",
                  "points": [],
                  "originPoint": {
                    "name": "origine",
                    "x": 0,
                    "y": 0
                  },
                  "centerPoint": {
                    "automatic": true,
                    "name": "centre",
                    "x": 0,
                    "y": 0
                  },
                  "customCollisionMask": []
                }
              ]
            }
          ]
        }
      ]
    }
  ],
  "objectsGroups": [],
  "variables": [],
  "layouts": [
    {
      "b": 211,
      "disableInputWhenNotFocused": true,
      "mangledName": "Base_32Scene",
      "name": "Base Scene",
      "oglFOV": 90,
      "oglZFar": 500,
      "oglZNear": 1,
      "r": 97,
      "standardSortMethod": true,
      "stopSoundsOnStartup": true,
      "title": "",
      "v": 201,
      "uiSettings": {
        "grid": false,
        "gridType": "rectangular",
        "gridWidth": 32,
        "gridHeight": 32,
        "gridOffsetX": 0,
        "gridOffsetY": 0,
        "gridColor": 10401023,
        "gridAlpha": 0.8,
        "snap": false,
        "zoomFactor": 0.8000000122070314,
        "windowMask": false
      },
      "objectsGroups": [],
      "variables": [],
      "instances": [
        {
          "angle": 0,
          "customSize": true,
          "height": 20,
          "layer": "",
          "locked": false,
          "name": "Ground_Tile",
          "persistentUuid": "98e7ae2e-f4e1-4e3a-968b-951eda70cc4f",
          "width": 631,
          "x": 79,
          "y": 531,
          "zOrder": 1,
          "numberProperties": [],
          "stringProperties": [],
          "initialVariables": []
        },
        {
          "angle": 0,
          "customSize": true,
          "height": 25,
          "layer": "",
          "locked": false,
          "name": "Ground_Tile",
          "persistentUuid": "167e44d5-afde-48ab-b510-480af9681897",
          "width": 151,
          "x": 444,
          "y": 449,
          "zOrder": 2,
          "numberProperties": [],
          "stringProperties": [],
          "initialVariables": []
        },
        {
          "angle": 0,
          "customSize": true,
          "height": 24,
          "layer": "",
          "locked": false,
          "name": "Ground_Tile",
          "persistentUuid": "886d57f1-98e9-4b17-88ea-7bf28f911dda",
          "width": 198,
          "x": 122,
          "y": 390,
          "zOrder": 3,
          "numberProperties": [],
          "stringProperties": [],
          "initialVariables": []
        },
        {
          "angle": 0,
          "customSize": true,
          "height": 24,
          "layer": "",
          "locked": false,
          "name": "Ground_Tile",
          "persistentUuid": "5b02fb50-3e9a-43e6-bb00-14e616d3a700",
          "width": 218,
          "x": 415,
          "y": 275,
          "zOrder": 4,
          "numberProperties": [],
          "stringProperties": [],
          "initialVariables": []
        },
        {
          "angle": 0,
          "customSize": true,
          "height": 22,
          "layer": "",
          "locked": false,
          "name": "Ground_Tile",
          "persistentUuid": "e470e844-0dc8-4ee2-8038-6f3bba961caa",
          "width": 214,
          "x": 216,
          "y": 115,
          "zOrder": 5,
          "numberProperties": [],
          "stringProperties": [],
          "initialVariables": []
        },
        {
          "angle": 0,
          "customSize": false,
          "height": 0,
          "layer": "",
          "locked": false,
          "name": "Crown",
          "persistentUuid": "c9624230-35e8-4b3b-8369-c5f7544374cd",
          "width": 0,
          "x": 244,
          "y": 69,
          "zOrder": 7,
          "numberProperties": [],
          "stringProperties": [],
          "initialVariables": []
        },
        {
          "angle": 0,
          "customSize": true,
          "height": 134,
          "layer": "",
          "locked": false,
          "name": "Ladder",
          "persistentUuid": "208d45e5-bd2e-4323-9412-4bf678acef40",
          "width": 61,
          "x": 600,
          "y": 406,
          "zOrder": 9,
          "numberProperties": [],
          "stringProperties": [],
          "initialVariables": []
        },
        {
          "angle": 0,
          "customSize": true,
          "height": 9,
          "layer": "",
          "locked": false,
          "name": "Hidden_Platform",
          "persistentUuid": "11ff2fda-ab0b-4c13-8edb-2a64b6389a39",
          "width": 112,
          "x": 65,
          "y": 309,
          "zOrder": 10,
          "numberProperties": [],
          "stringProperties": [],
          "initialVariables": []
        },
        {
          "angle": 0,
          "customSize": true,
          "height": 8,
          "layer": "",
          "locked": false,
          "name": "Hidden_Platform",
          "persistentUuid": "a442b7f1-6925-453c-aaf6-3cc130b32c6e",
          "width": 117,
          "x": 59,
          "y": 193,
          "zOrder": 11,
          "numberProperties": [],
          "stringProperties": [],
          "initialVariables": []
        },
        {
          "angle": 0,
          "customSize": true,
          "height": 23,
          "layer": "",
          "locked": false,
          "name": "Ground_Tile",
          "persistentUuid": "2c671d54-a323-4b82-806f-9785cacaec93",
          "width": 218,
          "x": 614,
          "y": 130,
          "zOrder": 4,
          "numberProperties": [],
          "stringProperties": [],
          "initialVariables": []
        },
        {
          "angle": 0,
          "customSize": true,
          "height": 172,
          "layer": "",
          "locked": false,
          "name": "Ladder",
          "persistentUuid": "064714ea-91fb-42a1-bd4e-de0328937e24",
          "width": 61,
          "x": 548,
          "y": 116,
          "zOrder": 9,
          "numberProperties": [],
          "stringProperties": [],
          "initialVariables": []
        },
        {
          "angle": 0,
          "customSize": true,
          "height": 9,
          "layer": "",
          "locked": false,
          "name": "Hidden_Platform",
          "persistentUuid": "e83dcf81-7b1c-4191-aeec-bb535d05be08",
          "width": 112,
          "x": -7,
          "y": 421,
          "zOrder": 10,
          "numberProperties": [],
          "stringProperties": [],
          "initialVariables": []
        },
        {
          "angle": 0,
          "customSize": true,
          "height": 44,
          "layer": "",
          "locked": false,
          "name": "Player",
          "persistentUuid": "2c813a6b-2d56-466d-af30-3aa0c5ad3b91",
          "width": 43,
          "x": 257,
          "y": 483,
          "zOrder": 13,
          "numberProperties": [],
          "stringProperties": [],
          "initialVariables": []
        }
      ],
      "objects": [
        {
          "assetStoreId": "",
          "height": 32,
          "name": "Ground_Tile",
          "tags": "",
          "texture": "Ground-1-1-1.png",
          "type": "TiledSpriteObject::TiledSprite",
          "width": 32,
          "variables": [],
          "effects": [],
          "behaviors": [
            {
              "name": "Platform",
              "type": "PlatformBehavior::PlatformBehavior",
              "canBeGrabbed": true,
              "platformType": "NormalPlatform",
              "yGrabOffset": 0
            }
          ]
        },
        {
          "assetStoreId": "",
          "name": "Crown",
          "tags": "",
          "type": "Sprite",
          "updateIfNotVisible": false,
          "variables": [],
          "effects": [],
          "behaviors": [],
          "animations": [
            {
              "name": "Crown",
              "useMultipleDirections": false,
              "directions": [
                {
                  "looping": false,
                  "timeBetweenFrames": 0.07999999821186066,
                  "sprites": [
                    {
                      "hasCustomCollisionMask": false,
                      "image": "Crown-1.png",
                      "points": [],
                      "originPoint": {
                        "name": "origine",
                        "x": 0,
                        "y": 0
                      },
                      "centerPoint": {
                        "automatic": true,
                        "name": "centre",
                        "x": 0,
                        "y": 0
                      },
                      "customCollisionMask": []
                    }
                  ]
                }
              ]
            }
          ]
        },
        {
          "assetStoreId": "",
          "height": 32,
          "name": "Ladder",
          "tags": "",
          "texture": "Ladder_Sprite-1-1.png",
          "type": "TiledSpriteObject::TiledSprite",
          "width": 32,
          "variables": [],
          "effects": [],
          "behaviors": [
            {
              "name": "Platform",
              "type": "PlatformBehavior::PlatformBehavior",
              "canBeGrabbed": true,
              "platformType": "Ladder",
              "yGrabOffset": 0
            }
          ]
        },
        {
          "assetStoreId": "",
          "height": 32,
          "name": "Hidden_Platform",
          "tags": "",
          "texture": "hidden_Platform-1.png",
          "type": "TiledSpriteObject::TiledSprite",
          "width": 32,
          "variables": [],
          "effects": [],
          "behaviors": [
            {
              "name": "Platform",
              "type": "PlatformBehavior::PlatformBehavior",
              "canBeGrabbed": true,
              "platformType": "Jumpthru",
              "yGrabOffset": 0
            }
          ]
        }
      ],
      "events": [
        {
          "colorB": 228,
          "colorG": 176,
          "colorR": 74,
          "creationTime": 0,
          "folded": true,
          "name": "Starting",
          "source": "",
          "type": "BuiltinCommonInstructions::Group",
          "events": [
            {
              "type": "BuiltinCommonInstructions::Standard",
              "conditions": [],
              "actions": []
            }
          ],
          "parameters": []
        },
        {
          "type": "BuiltinCommonInstructions::Standard",
          "conditions": [
            {
              "type": {
                "value": "DepartScene"
              },
              "parameters": [
                ""
              ]
            }
          ],
          "actions": [
            {
              "type": {
                "value": "Cache"
              },
              "parameters": [
                "Hidden_Platform"
              ]
            },
            {
              "type": {
                "value": "ModVarObjetTxt"
              },
              "parameters": [
                "Player",
                "direction",
                "=",
                "\"right\""
              ]
            }
          ]
        },
        {
          "colorB": 228,
          "colorG": 176,
          "colorR": 74,
          "creationTime": 0,
          "folded": true,
          "name": "WIn",
          "source": "",
          "type": "BuiltinCommonInstructions::Group",
          "events": [
            {
              "type": "BuiltinCommonInstructions::Standard",
              "conditions": [],
              "actions": []
            }
          ],
          "parameters": []
        },
        {
          "type": "BuiltinCommonInstructions::Standard",
          "conditions": [
            {
              "type": {
                "value": "CollisionNP"
              },
              "parameters": [
                "Player",
                "Crown",
                "",
                "",
                ""
              ]
            },
            {
              "type": {
                "value": "BuiltinCommonInstructions::Once"
              },
              "parameters": []
            }
          ],
          "actions": [
            {
              "type": {
                "value": "Delete"
              },
              "parameters": [
                "Crown",
                ""
              ]
            },
            {
              "type": {
                "value": "Scene"
              },
              "parameters": [
                "",
                "\"Scene2\"",
                ""
              ]
            },
            {
              "type": {
                "value": "PlaySound"
              },
              "parameters": [
                "",
                "mixkit-arcade-retro-changing-tab-206.wav",
                "",
                "",
                ""
              ]
            }
          ]
        },
        {
          "type": "BuiltinCommonInstructions::Standard",
          "conditions": [
            {
              "type": {
                "value": "CollisionNP"
              },
              "parameters": [
                "Player",
                "Hidden_Platform",
                "",
                "",
                ""
              ]
            }
          ],
          "actions": [
            {
              "type": {
                "value": "Montre"
              },
              "parameters": [
                "Hidden_Platform",
                ""
              ]
            }
          ]
        },
        {
          "colorB": 228,
          "colorG": 176,
          "colorR": 74,
          "creationTime": 0,
          "folded": true,
          "name": "Player Movement",
          "source": "",
          "type": "BuiltinCommonInstructions::Group",
          "events": [
            {
              "type": "BuiltinCommonInstructions::Standard",
              "conditions": [],
              "actions": []
            }
          ],
          "parameters": []
        },
        {
          "type": "BuiltinCommonInstructions::Standard",
          "conditions": [
            {
              "type": {
                "value": "KeyPressed"
              },
              "parameters": [
                "",
                "Left"
              ]
            }
          ],
          "actions": [
            {
              "type": {
                "value": "FlipX"
              },
              "parameters": [
                "Player",
                "yes"
              ]
            }
          ]
        },
        {
          "type": "BuiltinCommonInstructions::Standard",
          "conditions": [
            {
              "type": {
                "value": "KeyPressed"
              },
              "parameters": [
                "",
                "Right"
              ]
            }
          ],
          "actions": [
            {
              "type": {
                "value": "FlipX"
              },
              "parameters": [
                "Player",
                "no"
              ]
            }
          ]
        },
        {
          "type": "BuiltinCommonInstructions::Standard",
          "conditions": [
            {
              "type": {
                "value": "PlatformBehavior::IsOnFloor"
              },
              "parameters": [
                "Player",
                "PlatformerObject"
              ]
            }
          ],
          "actions": [
            {
              "type": {
                "value": "SetAnimationName"
              },
              "parameters": [
                "Player",
                "\"Idle\""
              ]
            }
          ]
        },
        {
          "type": "BuiltinCommonInstructions::Standard",
          "conditions": [
            {
              "type": {
                "value": "PlatformBehavior::PlatformerObjectBehavior::IsMovingEvenALittle"
              },
              "parameters": [
                "Player",
                "PlatformerObject"
              ]
            }
          ],
          "actions": [
            {
              "type": {
                "value": "SetAnimationName"
              },
              "parameters": [
                "Player",
                "\"Running\""
              ]
            }
          ]
        },
        {
          "type": "BuiltinCommonInstructions::Standard",
          "conditions": [
            {
              "type": {
                "value": "PlatformBehavior::IsOnLadder"
              },
              "parameters": [
                "Player",
                "PlatformerObject"
              ]
            }
          ],
          "actions": [
            {
              "type": {
                "value": "SetAnimationName"
              },
              "parameters": [
                "Player",
                "\"Ladder\""
              ]
            }
          ]
        },
        {
          "type": "BuiltinCommonInstructions::Standard",
          "conditions": [
            {
              "type": {
                "value": "PlatformBehavior::IsJumping"
              },
              "parameters": [
                "Player",
                "PlatformerObject"
              ]
            },
            {
              "type": {
                "value": "BuiltinCommonInstructions::Once"
              },
              "parameters": []
            }
          ],
          "actions": [
            {
              "type": {
                "value": "PlaySound"
              },
              "parameters": [
                "",
                "mixkit-player-jumping-in-a-video-game-2043.wav",
                "",
                "60",
                ""
              ]
            }
          ]
        },
        {
          "type": "BuiltinCommonInstructions::Standard",
          "conditions": [
            {
              "type": {
                "value": "PlatformBehavior::IsJumping"
              },
              "parameters": [
                "Player",
                "PlatformerObject"
              ]
            }
          ],
          "actions": [
            {
              "type": {
                "value": "SetAnimationName"
              },
              "parameters": [
                "Player",
                "\"Jumping\""
              ]
            }
          ]
        }
      ],
      "layers": [
        {
          "ambientLightColorB": 32,
          "ambientLightColorG": 0,
          "ambientLightColorR": 0,
          "followBaseLayerCamera": false,
          "isLightingLayer": false,
          "name": "",
          "visibility": true,
          "cameras": [
            {
              "defaultSize": true,
              "defaultViewport": true,
              "height": 0,
              "viewportBottom": 1,
              "viewportLeft": 0,
              "viewportRight": 1,
              "viewportTop": 0,
              "width": 0
            }
          ],
          "effects": []
        }
      ],
      "behaviorsSharedData": [
        {
          "name": "Platform",
          "type": "PlatformBehavior::PlatformBehavior"
        },
        {
          "name": "PlatformerObject",
          "type": "PlatformBehavior::PlatformerObjectBehavior"
        }
      ]
    },
    {
      "b": 0,
      "disableInputWhenNotFocused": true,
      "mangledName": "Scene2",
      "name": "Scene2",
      "oglFOV": 90,
      "oglZFar": 500,
      "oglZNear": 1,
      "r": 0,
      "standardSortMethod": true,
      "stopSoundsOnStartup": true,
      "title": "",
      "v": 0,
      "uiSettings": {
        "grid": false,
        "gridType": "rectangular",
        "gridWidth": 32,
        "gridHeight": 32,
        "gridOffsetX": 0,
        "gridOffsetY": 0,
        "gridColor": 10401023,
        "gridAlpha": 0.8,
        "snap": false,
        "zoomFactor": 1,
        "windowMask": false
      },
      "objectsGroups": [],
      "variables": [],
      "instances": [
        {
          "angle": 31.73232078552246,
          "customSize": true,
          "height": 18,
          "layer": "",
          "locked": false,
          "name": "Ground1",
          "persistentUuid": "340e61f3-1fd0-40e3-bcae-f6c94d9d768a",
          "width": 262,
          "x": 63.755210876464844,
          "y": 194.62710571289062,
          "zOrder": 1,
          "numberProperties": [],
          "stringProperties": [],
          "initialVariables": []
        },
        {
          "angle": 0,
          "customSize": true,
          "height": 34,
          "layer": "",
          "locked": false,
          "name": "Ground2",
          "persistentUuid": "1b4a3cd3-c824-4854-8427-ee6aea08ff83",
          "width": 334,
          "x": 11,
          "y": 557,
          "zOrder": 2,
          "numberProperties": [],
          "stringProperties": [],
          "initialVariables": []
        },
        {
          "angle": 0,
          "customSize": true,
          "height": 10,
          "layer": "",
          "locked": false,
          "name": "Ground3",
          "persistentUuid": "4912c893-2942-4abe-a494-8f6080f421e4",
          "width": 114,
          "x": 382,
          "y": 488,
          "zOrder": 3,
          "numberProperties": [],
          "stringProperties": [],
          "initialVariables": []
        },
        {
          "angle": 0,
          "customSize": true,
          "height": 10,
          "layer": "",
          "locked": false,
          "name": "Ground3",
          "persistentUuid": "88078be1-cf65-4e07-8566-1e6d250d8de2",
          "width": 114,
          "x": 231,
          "y": 400,
          "zOrder": 3,
          "numberProperties": [],
          "stringProperties": [],
          "initialVariables": []
        },
        {
          "angle": 0,
          "customSize": true,
          "height": 10,
          "layer": "",
          "locked": false,
          "name": "Ground3",
          "persistentUuid": "94e363ec-f35b-4a1d-b49d-6d9bb649e869",
          "width": 114,
          "x": 411,
          "y": 283,
          "zOrder": 3,
          "numberProperties": [],
          "stringProperties": [],
          "initialVariables": []
        },
        {
          "angle": 0,
          "customSize": true,
          "height": 608,
          "layer": "",
          "locked": false,
          "name": "Wall1",
          "persistentUuid": "95b2d19a-5f67-4446-ae3f-4fcabc1e48cd",
          "width": 61,
          "x": 736,
          "y": 0,
          "zOrder": 5,
          "numberProperties": [],
          "stringProperties": [],
          "initialVariables": []
        },
        {
          "angle": 0,
          "customSize": true,
          "height": 32,
          "layer": "",
          "locked": false,
          "name": "Wall1",
          "persistentUuid": "abb6c011-644d-4ee4-bb03-a0796f4dca58",
          "width": 797,
          "x": -2,
          "y": 3,
          "zOrder": 6,
          "numberProperties": [],
          "stringProperties": [],
          "initialVariables": []
        },
        {
          "angle": 0,
          "customSize": false,
          "height": 0,
          "layer": "",
          "locked": false,
          "name": "Heart",
          "persistentUuid": "955f4499-5cab-4a0d-a2c2-5d5f6c0ec3c3",
          "width": 0,
          "x": 114,
          "y": 109,
          "zOrder": 7,
          "numberProperties": [],
          "stringProperties": [],
          "initialVariables": []
        },
        {
          "angle": 0,
          "customSize": true,
          "height": 598,
          "layer": "",
          "locked": false,
          "name": "Wall1",
          "persistentUuid": "afc36451-cdf5-4c43-81e3-962171573d93",
          "width": 32,
          "x": -21,
          "y": 2,
          "zOrder": 8,
          "numberProperties": [],
          "stringProperties": [],
          "initialVariables": []
        },
        {
          "angle": 0,
          "customSize": false,
          "height": 0,
          "layer": "",
          "locked": false,
          "name": "Player",
          "persistentUuid": "11463bae-51af-42f2-9524-41057e1c2394",
          "width": 0,
          "x": 108,
          "y": 487,
          "zOrder": 9,
          "numberProperties": [],
          "stringProperties": [],
          "initialVariables": []
        },
        {
          "angle": 30.139183044433594,
          "customSize": true,
          "height": 31.88714599609375,
          "layer": "",
          "locked": false,
          "name": "Movement_Force",
          "persistentUuid": "7e958f6d-45d7-4877-b072-f83c42fb0fb7",
          "width": 292.963134765625,
          "x": 83.07039642333984,
          "y": 165.5756378173828,
          "zOrder": 10,
          "numberProperties": [],
          "stringProperties": [],
          "initialVariables": []
        },
        {
          "angle": 0,
          "customSize": true,
          "height": 352,
          "layer": "",
          "locked": false,
          "name": "Ladder",
          "persistentUuid": "22b86bbb-0115-4a68-b620-1481f6e84144",
          "width": 16,
          "x": 14,
          "y": 39,
          "zOrder": 11,
          "numberProperties": [],
          "stringProperties": [],
          "initialVariables": []
        }
      ],
      "objects": [
        {
          "assetStoreId": "",
          "height": 32,
          "name": "Ground1",
          "tags": "",
          "texture": "tile_01112.png",
          "type": "TiledSpriteObject::TiledSprite",
          "width": 32,
          "variables": [],
          "effects": [],
          "behaviors": [
            {
              "canBeGrabbed": true,
              "name": "Platform",
              "platformType": "NormalPlatform",
              "type": "PlatformBehavior::PlatformBehavior",
              "yGrabOffset": 0
            }
          ]
        },
        {
          "assetStoreId": "",
          "height": 32,
          "name": "Ground2",
          "tags": "",
          "texture": "tile_0009.png",
          "type": "TiledSpriteObject::TiledSprite",
          "width": 32,
          "variables": [],
          "effects": [],
          "behaviors": [
            {
              "canBeGrabbed": true,
              "name": "Platform",
              "platformType": "NormalPlatform",
              "type": "PlatformBehavior::PlatformBehavior",
              "yGrabOffset": 0
            }
          ]
        },
        {
          "assetStoreId": "",
          "height": 32,
          "name": "Ground3",
          "tags": "",
          "texture": "tile_0065.png",
          "type": "TiledSpriteObject::TiledSprite",
          "width": 32,
          "variables": [],
          "effects": [],
          "behaviors": [
            {
              "canBeGrabbed": true,
              "name": "Platform",
              "platformType": "Jumpthru",
              "type": "PlatformBehavior::PlatformBehavior",
              "yGrabOffset": 0
            }
          ]
        },
        {
          "assetStoreId": "",
          "height": 32,
          "name": "Wall1",
          "tags": "",
          "texture": "tile_0258.png",
          "type": "TiledSpriteObject::TiledSprite",
          "width": 32,
          "variables": [],
          "effects": [],
          "behaviors": [
            {
              "canBeGrabbed": true,
              "name": "Platform",
              "platformType": "NormalPlatform",
              "type": "PlatformBehavior::PlatformBehavior",
              "yGrabOffset": 0
            }
          ]
        },
        {
          "assetStoreId": "",
          "name": "Heart",
          "tags": "",
          "type": "Sprite",
          "updateIfNotVisible": false,
          "variables": [],
          "effects": [],
          "behaviors": [],
          "animations": [
            {
              "name": "",
              "useMultipleDirections": false,
              "directions": [
                {
                  "looping": true,
                  "timeBetweenFrames": 0.08,
                  "sprites": [
                    {
                      "hasCustomCollisionMask": false,
                      "image": "tile_0040.png",
                      "points": [],
                      "originPoint": {
                        "name": "origine",
                        "x": 0,
                        "y": 0
                      },
                      "centerPoint": {
                        "automatic": true,
                        "name": "centre",
                        "x": 0,
                        "y": 0
                      },
                      "customCollisionMask": []
                    },
                    {
                      "hasCustomCollisionMask": false,
                      "image": "tile_0041.png",
                      "points": [],
                      "originPoint": {
                        "name": "origine",
                        "x": 0,
                        "y": 0
                      },
                      "centerPoint": {
                        "automatic": true,
                        "name": "centre",
                        "x": 0,
                        "y": 0
                      },
                      "customCollisionMask": []
                    },
                    {
                      "hasCustomCollisionMask": false,
                      "image": "tile_0042.png",
                      "points": [],
                      "originPoint": {
                        "name": "origine",
                        "x": 0,
                        "y": 0
                      },
                      "centerPoint": {
                        "automatic": true,
                        "name": "centre",
                        "x": 0,
                        "y": 0
                      },
                      "customCollisionMask": []
                    }
                  ]
                }
              ]
            }
          ]
        },
        {
          "assetStoreId": "",
          "name": "Movement_Force",
          "tags": "",
          "type": "Sprite",
          "updateIfNotVisible": false,
          "variables": [],
          "effects": [],
          "behaviors": [],
          "animations": [
            {
              "name": "movementArrow",
              "useMultipleDirections": false,
              "directions": [
                {
                  "looping": false,
                  "timeBetweenFrames": 0.07999999821186066,
                  "sprites": [
                    {
                      "hasCustomCollisionMask": false,
                      "image": "movementArrow-1.png",
                      "points": [
                        {
                          "name": "tip",
                          "x": 30.61321449279785,
                          "y": 19.40566062927246
                        }
                      ],
                      "originPoint": {
                        "name": "origine",
                        "x": 0,
                        "y": 0
                      },
                      "centerPoint": {
                        "automatic": true,
                        "name": "centre",
                        "x": 0,
                        "y": 0
                      },
                      "customCollisionMask": []
                    }
                  ]
                }
              ]
            }
          ]
        },
        {
          "assetStoreId": "",
          "height": 32,
          "name": "Ladder",
          "tags": "",
          "texture": "tile_0120.png",
          "type": "TiledSpriteObject::TiledSprite",
          "width": 32,
          "variables": [],
          "effects": [],
          "behaviors": [
            {
              "canBeGrabbed": true,
              "name": "Platform",
              "platformType": "Ladder",
              "type": "PlatformBehavior::PlatformBehavior",
              "yGrabOffset": 0
            }
          ]
        }
      ],
      "events": [
        {
          "colorB": 228,
          "colorG": 176,
          "colorR": 74,
          "creationTime": 0,
          "folded": true,
          "name": "Starting",
          "source": "",
          "type": "BuiltinCommonInstructions::Group",
          "events": [
            {
              "type": "BuiltinCommonInstructions::Standard",
              "conditions": [],
              "actions": []
            }
          ],
          "parameters": []
        },
        {
          "type": "BuiltinCommonInstructions::Standard",
          "conditions": [
            {
              "type": {
                "value": "DepartScene"
              },
              "parameters": [
                ""
              ]
            }
          ],
          "actions": [
            {
              "type": {
                "value": "Cache"
              },
              "parameters": [
                "Movement_Force"
              ]
            },
            {
              "type": {
                "value": "Cache"
              },
              "parameters": [
                "Ladder"
              ]
            }
          ]
        },
        {
          "colorB": 228,
          "colorG": 176,
          "colorR": 74,
          "creationTime": 0,
          "name": "Win",
          "source": "",
          "type": "BuiltinCommonInstructions::Group",
          "events": [],
          "parameters": []
        },
        {
          "type": "BuiltinCommonInstructions::Standard",
          "conditions": [
            {
              "type": {
                "value": "CollisionNP"
              },
              "parameters": [
                "Player",
                "Heart",
                "",
                "",
                ""
              ]
            },
            {
              "type": {
                "value": "BuiltinCommonInstructions::Once"
              },
              "parameters": []
            }
          ],
          "actions": [
            {
              "type": {
                "value": "Delete"
              },
              "parameters": [
                "Heart",
                ""
              ]
            },
            {
              "type": {
                "value": "Scene"
              },
              "parameters": [
                "",
                "\"End scene\"",
                ""
              ]
            },
            {
              "type": {
                "value": "PlaySound"
              },
              "parameters": [
                "",
                "mixkit-arcade-retro-changing-tab-206.wav",
                "",
                "",
                ""
              ]
            }
          ]
        },
        {
          "colorB": 228,
          "colorG": 176,
          "colorR": 74,
          "creationTime": 0,
          "folded": true,
          "name": "Player Movement",
          "source": "",
          "type": "BuiltinCommonInstructions::Group",
          "events": [
            {
              "type": "BuiltinCommonInstructions::Standard",
              "conditions": [],
              "actions": []
            }
          ],
          "parameters": []
        },
        {
          "type": "BuiltinCommonInstructions::Standard",
          "conditions": [
            {
              "type": {
                "value": "KeyPressed"
              },
              "parameters": [
                "",
                "Right"
              ]
            }
          ],
          "actions": [
            {
              "type": {
                "value": "FlipX"
              },
              "parameters": [
                "Player",
                "no"
              ]
            }
          ]
        },
        {
          "type": "BuiltinCommonInstructions::Standard",
          "conditions": [
            {
              "type": {
                "value": "KeyPressed"
              },
              "parameters": [
                "",
                "Left"
              ]
            }
          ],
          "actions": [
            {
              "type": {
                "value": "FlipX"
              },
              "parameters": [
                "Player",
                "yes"
              ]
            }
          ]
        },
        {
          "type": "BuiltinCommonInstructions::Standard",
          "conditions": [
            {
              "type": {
                "value": "PlatformBehavior::IsJumping"
              },
              "parameters": [
                "Player",
                "PlatformerObject"
              ]
            },
            {
              "type": {
                "value": "BuiltinCommonInstructions::Once"
              },
              "parameters": []
            }
          ],
          "actions": [
            {
              "type": {
                "value": "SetAnimationName"
              },
              "parameters": [
                "Player",
                "\"Jumping\""
              ]
            },
            {
              "type": {
                "value": "PlaySound"
              },
              "parameters": [
                "",
                "mixkit-player-jumping-in-a-video-game-2043.wav",
                "",
                "60",
                ""
              ]
            }
          ]
        },
        {
          "type": "BuiltinCommonInstructions::Standard",
          "conditions": [
            {
              "type": {
                "value": "PlatformBehavior::IsOnFloor"
              },
              "parameters": [
                "Player",
                "PlatformerObject"
              ]
            }
          ],
          "actions": [
            {
              "type": {
                "value": "SetAnimationName"
              },
              "parameters": [
                "Player",
                "\"Idle\""
              ]
            }
          ]
        },
        {
          "type": "BuiltinCommonInstructions::Standard",
          "conditions": [
            {
              "type": {
                "value": "CollisionNP"
              },
              "parameters": [
                "Player",
                "Movement_Force",
                "",
                "",
                ""
              ]
            },
            {
              "type": {
                "value": "PlatformBehavior::IsOnFloor"
              },
              "parameters": [
                "Player",
                "PlatformerObject"
              ]
            }
          ],
          "actions": [
            {
              "type": {
                "value": "AddForceVersPos"
              },
              "parameters": [
                "Player",
                "Movement_Force.PointX(\"tip\")",
                "Movement_Force.PointY(\"tip\")",
                "25",
                ""
              ]
            }
          ]
        },
        {
          "type": "BuiltinCommonInstructions::Standard",
          "conditions": [
            {
              "type": {
                "value": "CollisionNP"
              },
              "parameters": [
                "Player",
                "Ladder",
                "",
                "",
                ""
              ]
            }
          ],
          "actions": [
            {
              "type": {
                "value": "Montre"
              },
              "parameters": [
                "Ladder",
                ""
              ]
            }
          ]
        }
      ],
      "layers": [
        {
          "ambientLightColorB": 7672752,
          "ambientLightColorG": 150995054,
          "ambientLightColorR": 1869182049,
          "followBaseLayerCamera": false,
          "isLightingLayer": false,
          "name": "",
          "visibility": true,
          "cameras": [
            {
              "defaultSize": true,
              "defaultViewport": true,
              "height": 0,
              "viewportBottom": 1,
              "viewportLeft": 0,
              "viewportRight": 1,
              "viewportTop": 0,
              "width": 0
            }
          ],
          "effects": []
        }
      ],
      "behaviorsSharedData": [
        {
          "name": "Platform",
          "type": "PlatformBehavior::PlatformBehavior"
        },
        {
          "name": "PlatformerObject",
          "type": "PlatformBehavior::PlatformerObjectBehavior"
        }
      ]
    },
    {
      "b": 210,
      "disableInputWhenNotFocused": true,
      "mangledName": "End_32scene",
      "name": "End scene",
      "oglFOV": 90,
      "oglZFar": 500,
      "oglZNear": 1,
      "r": 77,
      "standardSortMethod": true,
      "stopSoundsOnStartup": true,
      "title": "",
      "v": 219,
      "uiSettings": {
        "grid": false,
        "gridType": "rectangular",
        "gridWidth": 32,
        "gridHeight": 32,
        "gridOffsetX": 0,
        "gridOffsetY": 0,
        "gridColor": 10401023,
        "gridAlpha": 0.8,
        "snap": false,
        "zoomFactor": 1,
        "windowMask": false
      },
      "objectsGroups": [],
      "variables": [],
      "instances": [
        {
          "angle": 0,
          "customSize": true,
          "height": 452,
          "layer": "",
          "locked": false,
          "name": "Wall",
          "persistentUuid": "f538c82a-5877-4c78-a46f-23ed00647a11",
          "width": 44,
          "x": 754,
          "y": 0,
          "zOrder": 1,
          "numberProperties": [],
          "stringProperties": [],
          "initialVariables": []
        },
        {
          "angle": 0,
          "customSize": true,
          "height": 32,
          "layer": "",
          "locked": false,
          "name": "Wall",
          "persistentUuid": "3192f9fa-7604-42e2-8a26-6d656cdf5806",
          "width": 797,
          "x": 1,
          "y": 1,
          "zOrder": 2,
          "numberProperties": [],
          "stringProperties": [],
          "initialVariables": []
        },
        {
          "angle": 0,
          "customSize": true,
          "height": 600,
          "layer": "",
          "locked": false,
          "name": "Wall",
          "persistentUuid": "7c874d18-14f9-450b-81ca-0f349d20b80c",
          "width": 32,
          "x": 1,
          "y": 1,
          "zOrder": 3,
          "numberProperties": [],
          "stringProperties": [],
          "initialVariables": []
        },
        {
          "angle": 0,
          "customSize": true,
          "height": 32,
          "layer": "",
          "locked": false,
          "name": "Wall",
          "persistentUuid": "0728fb41-1068-40f1-b259-fb7ec9cde760",
          "width": 852,
          "x": 1,
          "y": 576,
          "zOrder": 4,
          "numberProperties": [],
          "stringProperties": [],
          "initialVariables": []
        },
        {
          "angle": 0,
          "customSize": false,
          "height": 0,
          "layer": "",
          "locked": false,
          "name": "ggText",
          "persistentUuid": "fa44d24b-534e-4bcb-acd4-6f227334dcc9",
          "width": 0,
          "x": 188,
          "y": 111,
          "zOrder": 6,
          "numberProperties": [],
          "stringProperties": [],
          "initialVariables": []
        },
        {
          "angle": 0,
          "customSize": false,
          "height": 0,
          "layer": "",
          "locked": false,
          "name": "Player",
          "persistentUuid": "2761b06d-b965-4b8c-81d5-90e63ef81b85",
          "width": 0,
          "x": 370,
          "y": 267,
          "zOrder": 7,
          "numberProperties": [],
          "stringProperties": [],
          "initialVariables": []
        },
        {
          "angle": 0,
          "customSize": true,
          "height": 368,
          "layer": "",
          "locked": false,
          "name": "goToMenu",
          "persistentUuid": "5bd40da5-7315-4f52-96f4-2927c26d84cf",
          "width": 122,
          "x": 817,
          "y": 207,
          "zOrder": 8,
          "numberProperties": [],
          "stringProperties": [],
          "initialVariables": []
        },
        {
          "angle": 0,
          "customSize": false,
          "height": 0,
          "layer": "",
          "locked": false,
          "name": "ToMenuText",
          "persistentUuid": "270146a3-f844-4e5c-8e9e-bc47703846f6",
          "width": 0,
          "x": 648,
          "y": 492,
          "zOrder": 9,
          "numberProperties": [],
          "stringProperties": [],
          "initialVariables": []
        }
      ],
      "objects": [
        {
          "assetStoreId": "",
          "height": 32,
          "name": "Wall",
          "tags": "",
          "texture": "tile_0011.png",
          "type": "TiledSpriteObject::TiledSprite",
          "width": 32,
          "variables": [],
          "effects": [],
          "behaviors": [
            {
              "canBeGrabbed": true,
              "name": "Platform",
              "platformType": "NormalPlatform",
              "type": "PlatformBehavior::PlatformBehavior",
              "yGrabOffset": 0
            }
          ]
        },
        {
          "assetStoreId": "",
          "bold": false,
          "italic": false,
          "name": "ggText",
          "smoothed": true,
          "tags": "",
          "type": "TextObject::Text",
          "underlined": false,
          "variables": [],
          "effects": [],
          "behaviors": [],
          "string": "You Won!",
          "font": "",
          "characterSize": 100,
          "color": {
            "b": 0,
            "g": 0,
            "r": 255
          }
        },
        {
          "assetStoreId": "",
          "name": "goToMenu",
          "tags": "",
          "type": "Sprite",
          "updateIfNotVisible": false,
          "variables": [],
          "effects": [],
          "behaviors": [],
          "animations": [
            {
              "name": "",
              "useMultipleDirections": false,
              "directions": [
                {
                  "looping": false,
                  "timeBetweenFrames": 0.08,
                  "sprites": [
                    {
                      "hasCustomCollisionMask": false,
                      "image": "tile_0209.png",
                      "points": [],
                      "originPoint": {
                        "name": "origine",
                        "x": 0,
                        "y": 0
                      },
                      "centerPoint": {
                        "automatic": true,
                        "name": "centre",
                        "x": 0,
                        "y": 0
                      },
                      "customCollisionMask": []
                    }
                  ]
                }
              ]
            }
          ]
        },
        {
          "assetStoreId": "",
          "bold": false,
          "italic": false,
          "name": "ToMenuText",
          "smoothed": true,
          "tags": "",
          "type": "TextObject::Text",
          "underlined": false,
          "variables": [],
          "effects": [],
          "behaviors": [],
          "string": "Main Menu ->",
          "font": "",
          "characterSize": 20,
          "color": {
            "b": 173,
            "g": 173,
            "r": 218
          }
        }
      ],
      "events": [
        {
          "type": "BuiltinCommonInstructions::Standard",
          "conditions": [
            {
              "type": {
                "value": "PlatformBehavior::IsOnFloor"
              },
              "parameters": [
                "Player",
                "PlatformerObject"
              ]
            }
          ],
          "actions": [
            {
              "type": {
                "value": "SetAnimationName"
              },
              "parameters": [
                "Player",
                "\"Idle\""
              ]
            }
          ]
        },
        {
          "type": "BuiltinCommonInstructions::Standard",
          "conditions": [
            {
              "type": {
                "value": "PlatformBehavior::PlatformerObjectBehavior::IsMovingEvenALittle"
              },
              "parameters": [
                "Player",
                "PlatformerObject"
              ]
            }
          ],
          "actions": [
            {
              "type": {
                "value": "SetAnimationName"
              },
              "parameters": [
                "Player",
                "\"Running\""
              ]
            }
          ]
        },
        {
          "type": "BuiltinCommonInstructions::Standard",
          "conditions": [
            {
              "type": {
                "value": "PlatformBehavior::IsOnLadder"
              },
              "parameters": [
                "Player",
                "PlatformerObject"
              ]
            }
          ],
          "actions": [
            {
              "type": {
                "value": "SetAnimationName"
              },
              "parameters": [
                "Player",
                "\"Ladder\""
              ]
            }
          ]
        },
        {
          "type": "BuiltinCommonInstructions::Standard",
          "conditions": [
            {
              "type": {
                "value": "KeyPressed"
              },
              "parameters": [
                "",
                "Left"
              ]
            }
          ],
          "actions": [
            {
              "type": {
                "value": "FlipX"
              },
              "parameters": [
                "Player",
                "yes"
              ]
            }
          ]
        },
        {
          "type": "BuiltinCommonInstructions::Standard",
          "conditions": [
            {
              "type": {
                "value": "KeyPressed"
              },
              "parameters": [
                "",
                "Right"
              ]
            }
          ],
          "actions": [
            {
              "type": {
                "value": "FlipX"
              },
              "parameters": [
                "Player",
                "no"
              ]
            }
          ]
        },
        {
          "type": "BuiltinCommonInstructions::Standard",
          "conditions": [
            {
              "type": {
                "value": "PlatformBehavior::IsJumping"
              },
              "parameters": [
                "Player",
                "PlatformerObject"
              ]
            },
            {
              "type": {
                "value": "BuiltinCommonInstructions::Once"
              },
              "parameters": []
            }
          ],
          "actions": [
            {
              "type": {
                "value": "PlaySound"
              },
              "parameters": [
                "",
                "mixkit-player-jumping-in-a-video-game-2043.wav",
                "",
                "60",
                ""
              ]
            }
          ]
        },
        {
          "type": "BuiltinCommonInstructions::Standard",
          "conditions": [
            {
              "type": {
                "value": "PlatformBehavior::IsJumping"
              },
              "parameters": [
                "Player",
                "PlatformerObject"
              ]
            }
          ],
          "actions": [
            {
              "type": {
                "value": "SetAnimationName"
              },
              "parameters": [
                "Player",
                "\"Jumping\""
              ]
            }
          ]
        },
        {
          "type": "BuiltinCommonInstructions::Standard",
          "conditions": [
            {
              "type": {
                "value": "CollisionNP"
              },
              "parameters": [
                "Player",
                "goToMenu",
                "",
                "",
                ""
              ]
            }
          ],
          "actions": [
            {
              "type": {
                "value": "Scene"
              },
              "parameters": [
                "",
                "\"Start Menu\"",
                ""
              ]
            }
          ]
        }
      ],
      "layers": [
        {
          "ambientLightColorB": 8218448,
          "ambientLightColorG": 150995054,
          "ambientLightColorR": 1869182049,
          "followBaseLayerCamera": false,
          "isLightingLayer": false,
          "name": "",
          "visibility": true,
          "cameras": [
            {
              "defaultSize": true,
              "defaultViewport": true,
              "height": 0,
              "viewportBottom": 1,
              "viewportLeft": 0,
              "viewportRight": 1,
              "viewportTop": 0,
              "width": 0
            }
          ],
          "effects": []
        }
      ],
      "behaviorsSharedData": [
        {
          "name": "Platform",
          "type": "PlatformBehavior::PlatformBehavior"
        },
        {
          "name": "PlatformerObject",
          "type": "PlatformBehavior::PlatformerObjectBehavior"
        }
      ]
    },
    {
      "b": 114,
      "disableInputWhenNotFocused": true,
      "mangledName": "Scene3",
      "name": "Scene3",
      "oglFOV": 90,
      "oglZFar": 500,
      "oglZNear": 1,
      "r": 114,
      "standardSortMethod": true,
      "stopSoundsOnStartup": true,
      "title": "",
      "v": 114,
      "uiSettings": {
        "grid": false,
        "gridType": "rectangular",
        "gridWidth": 32,
        "gridHeight": 32,
        "gridOffsetX": 0,
        "gridOffsetY": 0,
        "gridColor": 10401023,
        "gridAlpha": 0.8,
        "snap": false,
        "zoomFactor": 1,
        "windowMask": false
      },
      "objectsGroups": [],
      "variables": [],
      "instances": [
        {
          "angle": 0,
          "customSize": true,
          "height": 17,
          "layer": "",
          "locked": false,
          "name": "Ground1",
          "persistentUuid": "d835f06c-614a-4489-963b-5ce62fe3a9b9",
          "width": 966,
          "x": -164,
          "y": 583,
          "zOrder": 1,
          "numberProperties": [],
          "stringProperties": [],
          "initialVariables": []
        },
        {
          "angle": 0,
          "customSize": false,
          "height": 0,
          "layer": "",
          "locked": false,
          "name": "Player",
          "persistentUuid": "9abf4b27-2bf2-4c33-85d4-fd7f5e66e233",
          "width": 0,
          "x": 8,
          "y": 513,
          "zOrder": 2,
          "numberProperties": [],
          "stringProperties": [],
          "initialVariables": []
        }
      ],
      "objects": [
        {
          "assetStoreId": "",
          "height": 32,
          "name": "Ground1",
          "tags": "",
          "texture": "tile_0253.png",
          "type": "TiledSpriteObject::TiledSprite",
          "width": 32,
          "variables": [],
          "effects": [],
          "behaviors": [
            {
              "canBeGrabbed": true,
              "name": "Platform",
              "platformType": "NormalPlatform",
              "type": "PlatformBehavior::PlatformBehavior",
              "yGrabOffset": 0
            }
          ]
        }
      ],
      "events": [
        {
          "type": "BuiltinCommonInstructions::Standard",
          "conditions": [],
          "actions": [
            {
              "type": {
                "value": "CentreCamera"
              },
              "parameters": [
                "",
                "Player",
                "",
                "",
                ""
              ]
            }
          ]
        }
      ],
      "layers": [
        {
          "ambientLightColorB": 1,
          "ambientLightColorG": 134217728,
          "ambientLightColorR": 1597066561,
          "followBaseLayerCamera": false,
          "isLightingLayer": false,
          "name": "",
          "visibility": true,
          "cameras": [
            {
              "defaultSize": true,
              "defaultViewport": true,
              "height": 0,
              "viewportBottom": 1,
              "viewportLeft": 0,
              "viewportRight": 1,
              "viewportTop": 0,
              "width": 0
            }
          ],
          "effects": []
        }
      ],
      "behaviorsSharedData": [
        {
          "name": "Platform",
          "type": "PlatformBehavior::PlatformBehavior"
        },
        {
          "name": "PlatformerObject",
          "type": "PlatformBehavior::PlatformerObjectBehavior"
        }
      ]
    },
    {
      "b": 168,
      "disableInputWhenNotFocused": true,
      "mangledName": "Start_32Menu",
      "name": "Start Menu",
      "oglFOV": 90,
      "oglZFar": 500,
      "oglZNear": 1,
      "r": 86,
      "standardSortMethod": true,
      "stopSoundsOnStartup": true,
      "title": "",
      "v": 57,
      "uiSettings": {
        "grid": false,
        "gridType": "rectangular",
        "gridWidth": 32,
        "gridHeight": 32,
        "gridOffsetX": 0,
        "gridOffsetY": 0,
        "gridColor": 10401023,
        "gridAlpha": 0.8,
        "snap": false,
        "zoomFactor": 1,
        "windowMask": false
      },
      "objectsGroups": [],
      "variables": [],
      "instances": [
        {
          "angle": 0,
          "customSize": false,
          "height": 0,
          "layer": "",
          "locked": false,
          "name": "Play_Button",
          "persistentUuid": "a376fbf4-eff9-4049-ab83-7784e75159b6",
          "width": 0,
          "x": 316,
          "y": 166,
          "zOrder": 1,
          "numberProperties": [],
          "stringProperties": [],
          "initialVariables": []
        },
        {
          "angle": 0,
          "customSize": true,
          "height": 148,
          "layer": "",
          "locked": false,
          "name": "NewSprite",
          "persistentUuid": "91fc3b44-fb89-4834-960d-02ecc5e2ba02",
          "width": 329,
          "x": 231,
          "y": 149,
          "zOrder": 2,
          "numberProperties": [],
          "stringProperties": [],
          "initialVariables": []
        },
        {
          "angle": 0,
          "customSize": false,
          "height": 0,
          "layer": "",
          "locked": false,
          "name": "Insturction",
          "persistentUuid": "47637af7-8efa-4678-a54b-522dede5db0b",
          "width": 0,
          "x": 282,
          "y": 306,
          "zOrder": 3,
          "numberProperties": [],
          "stringProperties": [],
          "initialVariables": []
        }
      ],
      "objects": [
        {
          "assetStoreId": "",
          "name": "NewSprite",
          "tags": "",
          "type": "Sprite",
          "updateIfNotVisible": false,
          "variables": [],
          "effects": [],
          "behaviors": [],
          "animations": [
            {
              "name": "",
              "useMultipleDirections": false,
              "directions": [
                {
                  "looping": false,
                  "timeBetweenFrames": 0.08,
                  "sprites": [
                    {
                      "hasCustomCollisionMask": false,
                      "image": "tile_0000.png",
                      "points": [],
                      "originPoint": {
                        "name": "origine",
                        "x": 0,
                        "y": 0
                      },
                      "centerPoint": {
                        "automatic": true,
                        "name": "centre",
                        "x": 0,
                        "y": 0
                      },
                      "customCollisionMask": []
                    }
                  ]
                }
              ]
            }
          ]
        },
        {
          "assetStoreId": "",
          "bold": false,
          "italic": false,
          "name": "Play_Button",
          "smoothed": true,
          "tags": "",
          "type": "TextObject::Text",
          "underlined": false,
          "variables": [],
          "effects": [],
          "behaviors": [],
          "string": "Play",
          "font": "",
          "characterSize": 100,
          "color": {
            "b": 114,
            "g": 160,
            "r": 50
          }
        },
        {
          "assetStoreId": "",
          "bold": false,
          "italic": false,
          "name": "Insturction",
          "smoothed": true,
          "tags": "",
          "type": "TextObject::Text",
          "underlined": false,
          "variables": [],
          "effects": [],
          "behaviors": [],
          "string": "Press ENTER or click PLAY",
          "font": "",
          "characterSize": 20,
          "color": {
            "b": 0,
            "g": 0,
            "r": 0
          }
        }
      ],
      "events": [
        {
          "colorB": 228,
          "colorG": 176,
          "colorR": 74,
          "creationTime": 0,
          "folded": true,
          "name": "Starting",
          "source": "",
          "type": "BuiltinCommonInstructions::Group",
          "events": [
            {
              "type": "BuiltinCommonInstructions::Standard",
              "conditions": [],
              "actions": []
            }
          ],
          "parameters": []
        },
        {
          "type": "BuiltinCommonInstructions::Standard",
          "conditions": [
            {
              "type": {
                "value": "DepartScene"
              },
              "parameters": [
                ""
              ]
            }
          ],
          "actions": [
            {
              "type": {
                "value": "Cache"
              },
              "parameters": [
                "NewSprite"
              ]
            }
          ]
        },
        {
          "type": "BuiltinCommonInstructions::Standard",
          "conditions": [
            {
              "type": {
                "value": "SourisSurObjet"
              },
              "parameters": [
                "NewSprite",
                "",
                "",
                ""
              ]
            },
            {
              "type": {
                "value": "MouseButtonFromTextPressed"
              },
              "parameters": [
                "",
                "\"Left\""
              ]
            }
          ],
          "actions": [
            {
              "type": {
                "value": "Scene"
              },
              "parameters": [
                "",
                "\"Base Scene\"",
                ""
              ]
            }
          ]
        },
        {
          "type": "BuiltinCommonInstructions::Standard",
          "conditions": [
            {
              "type": {
                "value": "BuiltinCommonInstructions::Or"
              },
              "parameters": [],
              "subInstructions": [
                {
                  "type": {
                    "value": "KeyPressed"
                  },
                  "parameters": [
                    "",
                    "Return"
                  ]
                },
                {
                  "type": {
                    "value": "BuiltinCommonInstructions::And"
                  },
                  "parameters": [],
                  "subInstructions": [
                    {
                      "type": {
                        "value": "MouseButtonFromTextPressed"
                      },
                      "parameters": [
                        "",
                        "\"Left\""
                      ]
                    },
                    {
                      "type": {
                        "value": "SourisSurObjet"
                      },
                      "parameters": [
                        "NewSprite",
                        "",
                        "",
                        ""
                      ]
                    }
                  ]
                }
              ]
            }
          ],
          "actions": [
            {
              "type": {
                "value": "Scene"
              },
              "parameters": [
                "",
                "\"Base Scene\"",
                ""
              ]
            }
          ]
        },
        {
          "type": "BuiltinCommonInstructions::Standard",
          "conditions": [],
          "actions": []
        },
        {
          "type": "BuiltinCommonInstructions::Standard",
          "conditions": [],
          "actions": []
        }
      ],
      "layers": [
        {
          "ambientLightColorB": 8698768,
          "ambientLightColorG": 150995054,
          "ambientLightColorR": 1869182049,
          "followBaseLayerCamera": false,
          "isLightingLayer": false,
          "name": "",
          "visibility": true,
          "cameras": [
            {
              "defaultSize": true,
              "defaultViewport": true,
              "height": 0,
              "viewportBottom": 1,
              "viewportLeft": 0,
              "viewportRight": 1,
              "viewportTop": 0,
              "width": 0
            }
          ],
          "effects": []
        }
      ],
      "behaviorsSharedData": [
        {
          "name": "PlatformerObject",
          "type": "PlatformBehavior::PlatformerObjectBehavior"
        }
      ]
    }
  ],
  "externalEvents": [],
  "eventsFunctionsExtensions": [],
  "externalLayouts": [],
  "externalSourceFiles": []
}